hydra_email_manager/__init__.py
hydra_email_manager/HydraEmailManager.py
hydra_email_manager-0.1.37.dist-info/LICENSE
hydra_email_manager-0.1.37.dist-info/METADATA
hydra_email_manager-0.1.37.dist-info/WHEEL
hydra_email_manager-0.1.37.dist-info/RECORD
