Metadata-Version: 2.3
Name: hydra-email-manager
Version: 0.1.37
Summary: Gerenciador de email office 365
Author: Ronaldo da Rocha
Author-email: ronaldo.rocha.jimmy@gmail.com
Requires-Python: >=3.12
Classifier: Programming Language :: Python :: 3
Classifier: Programming Language :: Python :: 3.12
Classifier: Programming Language :: Python :: 3.13
